mathinator/__init__.py
mathinator/__main__.py
mathinator/utils.py
Mathinator-1.0.1.dist-info/LICENSE
Mathinator-1.0.1.dist-info/METADATA
Mathinator-1.0.1.dist-info/WHEEL
Mathinator-1.0.1.dist-info/top_level.txt
Mathinator-1.0.1.dist-info/RECORD
