Metadata-Version: 2.1
Name: Mathinator
Version: 1.0.1
Summary: A command line tool to do hard math quickly
Home-page: https://github.com/mordy-python/Mathinator
Author: Israel Waldner
Author-email: imky171@gmail.com
License: UNKNOWN
Project-URL: Bug Tracker, https://github.com/mordy-python/Mathinator/issues
Platform: UNKNOWN
Classifier: Programming Language :: Python :: 3
Classifier: License :: OSI Approved :: MIT License
Classifier: Operating System :: OS Independent
Requires-Python: >=3.6
License-File: LICENSE
Requires-Dist: click
